robsblobs/G0_brilliance.py
robsblobs/__init__.py
robsblobs/alices_damn_monitor.py
robsblobs/atd95.py
robsblobs/atd95_test.py
robsblobs/brightness_ranking.py
robsblobs/cie_monitor_helpers.py
robsblobs/cie_standard.py
robsblobs/cmfs.py
robsblobs/data/ciexyz31_1.csv
robsblobs/data/ciexyzjv.csv
robsblobs/data/linss2_10e_1.csv
robsblobs/dkl.py
robsblobs/dkl_setup.py
robsblobs/fairchildL.py
robsblobs/funny_dude_discovers_maxRGB_in_adobe.py
robsblobs/guth_vector.py
robsblobs/hsv.py
robsblobs/hue_angles.py
robsblobs/hunt.py
robsblobs/hunt_test.py
robsblobs/illuminants.py
robsblobs/img_stats.py
robsblobs/infamous_lab.py
robsblobs/jazzy.py
robsblobs/jingHSP.py
robsblobs/lch.py
robsblobs/lms.py
robsblobs/macadam.py
robsblobs/matlab.py
robsblobs/maxRGB_revolution.py
robsblobs/monitor.py
robsblobs/monitor_fitting.py
robsblobs/nayatani_insanity.py
robsblobs/nayatani_test.py
robsblobs/plotting.py
robsblobs/radiance.py
robsblobs/rgb.py
robsblobs/spectra.py
robsblobs/strobe_export.py
robsblobs/sumrgb.py
robsblobs/svf.py
robsblobs/uv_space.py
robsblobs/ware_cowan.py
robsblobs-0.1.1.dist-info/LICENSE
robsblobs-0.1.1.dist-info/METADATA
robsblobs-0.1.1.dist-info/WHEEL
robsblobs-0.1.1.dist-info/RECORD
